dynamsoft_barcode_reader_bundle/_DynamsoftCore.cpython-311-aarch64-linux-gnu.so
dynamsoft_barcode_reader_bundle/__init__.py
dynamsoft_barcode_reader_bundle/_DynamsoftCaptureVisionRouter.cpython-311-aarch64-linux-gnu.so
dynamsoft_barcode_reader_bundle/core.py
dynamsoft_barcode_reader_bundle/utility.py
dynamsoft_barcode_reader_bundle/libDynamicPdf.so
dynamsoft_barcode_reader_bundle/libDynamsoftNeuralNetwork.so
dynamsoft_barcode_reader_bundle/libDynamsoftUtility.so
dynamsoft_barcode_reader_bundle/_DynamsoftUtility.cpython-311-aarch64-linux-gnu.so
dynamsoft_barcode_reader_bundle/libDynamsoftBarcodeReader.so
dynamsoft_barcode_reader_bundle/_DynamsoftLicense.cpython-311-aarch64-linux-gnu.so
dynamsoft_barcode_reader_bundle/dip.py
dynamsoft_barcode_reader_bundle/dnn.py
dynamsoft_barcode_reader_bundle/dbr.py
dynamsoft_barcode_reader_bundle/_DynamsoftImageProcessing.cpython-311-aarch64-linux-gnu.so
dynamsoft_barcode_reader_bundle/libDynamsoftCore.so
dynamsoft_barcode_reader_bundle/_DynamsoftBarcodeReader.cpython-311-aarch64-linux-gnu.so
dynamsoft_barcode_reader_bundle/libDynamsoftImageProcessing.so
dynamsoft_barcode_reader_bundle/libDynamsoftLicense.so
dynamsoft_barcode_reader_bundle/license.py
dynamsoft_barcode_reader_bundle/cvr.py
dynamsoft_barcode_reader_bundle/libDynamsoftCaptureVisionRouter.so
dynamsoft_barcode_reader_bundle/Templates/DBR-PresetTemplates.json
dynamsoft_barcode_reader_bundle/Models/Code128Decoder.data
dynamsoft_barcode_reader_bundle/Models/OneDLocalization.data
dynamsoft_barcode_reader_bundle/Models/EAN13Decoder.data
dynamsoft_barcode_reader_bundle/Models/OneDDeblur.data
dynamsoft_barcode_reader_bundle/Models/DataMatrixQRCodeLocalization.data
dynamsoft_barcode_reader_bundle-11.2.5000.dist-info/RECORD
dynamsoft_barcode_reader_bundle-11.2.5000.dist-info/WHEEL
dynamsoft_barcode_reader_bundle-11.2.5000.dist-info/top_level.txt
dynamsoft_barcode_reader_bundle-11.2.5000.dist-info/METADATA
dynamsoft_barcode_reader_bundle-11.2.5000.dist-info/licenses/LICENSE.txt
